snapshot_phantomjs/__init__.py
snapshot_phantomjs/_version.py
snapshot_phantomjs/snapshot.py
snapshot_phantomjs/phantomjs/snapshot.js
snapshot_phantomjs-0.0.3.dist-info/METADATA
snapshot_phantomjs-0.0.3.dist-info/WHEEL
snapshot_phantomjs-0.0.3.dist-info/top_level.txt
snapshot_phantomjs-0.0.3.dist-info/RECORD
