Metadata-Version: 1.1
Name: snapshot-phantomjs
Version: 0.0.3
Summary: Render pyecharts as image via phantomjs
Home-page: https://github.com/pyecharts/snapshot-phantomjs
Author: pyecharts dev team
Author-email: info@pyecharts.com
License: MIT
Download-URL: https://github.com/pyecharts/snapshot-phantomjs/archive/0.0.3.tar.gz
Keywords: python,pyecharts,chart
Platform: UNKNOWN
Classifier: Topic :: Software Development :: Libraries
Classifier: Programming Language :: Python
Classifier: Intended Audience :: Developers
Classifier: Programming Language :: Python :: 3 :: Only
Classifier: Programming Language :: Python :: 3.5
Classifier: Programming Language :: Python :: 3.6
Classifier: Programming Language :: Python :: 3.7
Classifier: Programming Language :: Python :: 3.8
